server_pakage/__init__.py
server_pakage/server.py
my_messenger_server-0.1.dist-info/METADATA
my_messenger_server-0.1.dist-info/WHEEL
my_messenger_server-0.1.dist-info/top_level.txt
my_messenger_server-0.1.dist-info/RECORD
